{
 "name":"Hard Reparator",
 "size":2,
 "category":"effect",
 "requirements":[
 {
     "item":"silicon",
     "amount":"650"
 },
 {
     "item":"copper",
     "amount":"400"
 },
 {
     "item":"lead",
     "amount":"400"
 },
 {
     "item":"plastanium",
     "amount":"50"
 },
 {
     "item":"titanium",
     "amount":"240"
 }
 ],
 "liquidCapacity":30,
 "health":400,
 "baseColor":"aaccee",
 "type":"MendProjector",
 "armor":30,
 "buildCostMultiplier":8,
 "reload":6,
 "range":160,
 "healPercent":0.2,
 "consumes": {
     "power":4
 }, 
"nuderBullets":false,
"conductivePower":true,
"hasLiquids" :true,
"itemCapacity":15
"research":"warpgate",
}
